qa_pytest_examples-0.0.13.dist-info/METADATA
qa_pytest_examples-0.0.13.dist-info/WHEEL
qa_pytest_examples-0.0.13.dist-info/entry_points.txt
qa_pytest_examples/__init__.py
qa_pytest_examples/_version.py
qa_pytest_examples/combined_configuration.py
qa_pytest_examples/combined_steps.py
qa_pytest_examples/configurations/combined_configuration.ini
qa_pytest_examples/configurations/pw_terminalx_configuration.ini
qa_pytest_examples/configurations/rabbitmq_self_configuration.ini
qa_pytest_examples/configurations/swagger_petstore_configuration.ini
qa_pytest_examples/configurations/terminalx_configuration.ini
qa_pytest_examples/logging.ini
qa_pytest_examples/model/__init__.py
qa_pytest_examples/model/credentials.py
qa_pytest_examples/model/swagger_petstore_credentials.py
qa_pytest_examples/model/swagger_petstore_pet.py
qa_pytest_examples/model/terminalx_credentials.py
qa_pytest_examples/model/terminalx_user.py
qa_pytest_examples/pw_terminalx_configuration.py
qa_pytest_examples/pw_terminalx_steps.py
qa_pytest_examples/rabbitmq_self_configuration.py
qa_pytest_examples/swagger_petstore_configuration.py
qa_pytest_examples/swagger_petstore_steps.py
qa_pytest_examples/terminalx_configuration.py
qa_pytest_examples/terminalx_steps.py
qa_pytest_examples/terminalx_users_configuration.py
qa_pytest_examples-0.0.13.dist-info/RECORD
